stef/Dockerfile
stef/__init__.py
stef/base.py
stef/bashrunner.py
stef/dockerrunner.py
stef/logger.py
stef/runner.py
stef/scripts/__init__.py
stef/scripts/runtests.py
stef-1.0.9.dist-info/licenses/LICENSE
stef-1.0.9.dist-info/METADATA
stef-1.0.9.dist-info/WHEEL
stef-1.0.9.dist-info/entry_points.txt
stef-1.0.9.dist-info/top_level.txt
stef-1.0.9.dist-info/RECORD
