Metadata-Version: 2.4
Name: stef
Version: 1.0.9
Summary: Submission TEst Framework
Author-email: Gina Muuss <muuss@uni-bonn.de>, Lennart Buhl <buhl@cs.uni-bonn.de>
Project-URL: Homepage, https://github.com/GinaMuuss/stef
Classifier: Programming Language :: Python :: 3
Classifier: License :: OSI Approved :: MIT License
Classifier: Operating System :: OS Independent
Requires-Python: >=3.6
License-File: LICENSE
Requires-Dist: docker>=4.3.0
Requires-Dist: termcolor>=1.1.0
Dynamic: license-file
